LICENSE
README.md
setup.py
eth_fn/__init__.py
eth_fn.egg-info/PKG-INFO
eth_fn.egg-info/SOURCES.txt
eth_fn.egg-info/dependency_links.txt
eth_fn.egg-info/not-zip-safe
eth_fn.egg-info/requires.txt
eth_fn.egg-info/top_level.txt