Metadata-Version: 2.1
Name: eth-fn
Version: 0.1
Summary: eth_fn: Simple Python utilities for web3py to call ETH contract without ABI
Home-page: https://github.com/kernel1983/eth-fn
Author: 0xKJ
Author-email: kernel1983@gmail.com
License: MIT
Keywords: ethereum
Platform: UNKNOWN
Classifier: Intended Audience :: Developers
Classifier: License :: OSI Approved :: MIT License
Classifier: Natural Language :: English
Classifier: Programming Language :: Python :: 3
Requires-Python: >=3.8, <4
License-File: LICENSE
